onepasswordconnectsdkopexe/__init__.py
onepasswordconnectsdkopexe/bin/op.exe
onepasswordconnectsdkopexe/client.py
onepasswordconnectsdkopexe/client.py.bak
onepasswordconnectsdkopexe/config.py
onepasswordconnectsdkopexe/models/__init__.py
onepasswordconnectsdkopexe/models/constants.py
onepasswordconnectsdkopexe/models/op_error.py
onepasswordconnectsdkopexe/models/op_field.py
onepasswordconnectsdkopexe/models/op_field_section.py
onepasswordconnectsdkopexe/models/op_item.py
onepasswordconnectsdkopexe/models/op_item_details.py
onepasswordconnectsdkopexe/models/op_item_urls.py
onepasswordconnectsdkopexe/models/op_item_vault.py
onepasswordconnectsdkopexe/models/op_section.py
onepasswordconnectsdkopexe/models/op_summary_item.py
onepasswordconnectsdkopexe/models/op_vault.py
onepasswordconnectsdkopexe-0.1.5.dist-info/LICENSE
onepasswordconnectsdkopexe-0.1.5.dist-info/WHEEL
onepasswordconnectsdkopexe-0.1.5.dist-info/METADATA
onepasswordconnectsdkopexe-0.1.5.dist-info/RECORD
