Metadata-Version: 2.1
Name: onepasswordconnectsdkopexe
Version: 0.1.5
Summary: Python SDK for 1Password Connect with OP.exe 
Home-page: https://github.com/MSF-OCB/connect-sdk-python_opexe
License: MIT
Author: MSF-OCB
Requires-Python: >=3.7,<4.0
Classifier: License :: OSI Approved :: MIT License
Classifier: Programming Language :: Python :: 3
Classifier: Programming Language :: Python :: 3.7
Classifier: Programming Language :: Python :: 3.8
Classifier: Programming Language :: Python :: 3.9
Requires-Dist: onepasswordconnectsdk (>=1.1.0,<2.0.0)
Requires-Dist: python-dateutil (>=2.8.2,<3.0.0)
Requires-Dist: six (>=1.16.0,<2.0.0)
Project-URL: Bug Tracker, https://github.com/MSF-OCB/connect-sdk-python_opexe/issues
Project-URL: Repository, https://github.com/MSF-OCB/connect-sdk-python_opexe
